sit4onnxw/__init__.py
sit4onnxw/cli.py
sit4onnxw/web_inference.py
sit4onnxw-1.0.2.dist-info/licenses/LICENSE
tests/__init__.py
tests/test_cli.py
tests/test_web_inference.py
sit4onnxw-1.0.2.dist-info/METADATA
sit4onnxw-1.0.2.dist-info/WHEEL
sit4onnxw-1.0.2.dist-info/entry_points.txt
sit4onnxw-1.0.2.dist-info/top_level.txt
sit4onnxw-1.0.2.dist-info/RECORD
