Metadata-Version: 2.4
Name: sit4onnxw
Version: 1.0.2
Summary: Simple Inference Test for ONNX Runtime Web
Home-page: https://github.com/PINTO0309/sit4onnxw
Author: Katsuya Hyodo
Author-email: 
Classifier: Programming Language :: Python :: 3
Classifier: License :: OSI Approved :: MIT License
Classifier: Operating System :: OS Independent
Requires-Python: >=3.10
License-File: LICENSE
Requires-Dist: numpy>=1.19.0
Requires-Dist: onnx>=1.12.0
Requires-Dist: click>=8.0.0
Requires-Dist: requests>=2.25.0
Requires-Dist: selenium>=4.0.0
Requires-Dist: webdriver-manager>=3.8.0
Dynamic: author
Dynamic: classifier
Dynamic: description
Dynamic: description-content-type
Dynamic: home-page
Dynamic: license-file
Dynamic: requires-dist
Dynamic: requires-python
Dynamic: summary
